{"login": "yuishiha", "display_name": "Yui Ishihara", "image_small": "https://cdn.intra.42.fr/users/4cdce1fea3ee75243daf7630156186eb/small_yuishiha.jpg", "piscine_start": "2026-02-02", "piscine_end": "2026-02-27", "piscine_days": 26, "target_hours_per_day": 8, "total_target_hours": 208, "total_logged_hours": 128.74, "elapsed_days": 20.12, "elapsed_hours": 482.82, "avg_hours_per_day": 6.4, "remaining_days": 5.88, "remaining_hours_needed": 79.26, "required_avg_remaining": 13.47, "progress_pct": 61.9, "diff_from_target": -32.2, "on_track": false, "is_active": false, "active_extra_hours": 0.0, "daily": [{"date": "2026-02-02", "weekday": "Mon", "hours": 6.54, "met_target": false}, {"date": "2026-02-03", "weekday": "Tue", "hours": 4.25, "met_target": false}, {"date": "2026-02-04", "weekday": "Wed", "hours": 5.75, "met_target": false}, {"date": "2026-02-05", "weekday": "Thu", "hours": 4.24, "met_target": false}, {"date": "2026-02-06", "weekday": "Fri", "hours": 2.05, "met_target": false}, {"date": "2026-02-07", "weekday": "Sat", "hours": 10.8, "met_target": true}, {"date": "2026-02-08", "weekday": "Sun", "hours": 10.35, "met_target": true}, {"date": "2026-02-09", "weekday": "Mon", "hours": 3.0, "met_target": false}, {"date": "2026-02-10", "weekday": "Tue", "hours": 6.95, "met_target": false}, {"date": "2026-02-11", "weekday": "Wed", "hours": 7.29, "met_target": false}, {"date": "2026-02-12", "weekday": "Thu", "hours": 9.46, "met_target": true}, {"date": "2026-02-13", "weekday": "Fri", "hours": 0, "met_target": false}, {"date": "2026-02-14", "weekday": "Sat", "hours": 8.05, "met_target": true}, {"date": "2026-02-15", "weekday": "Sun", "hours": 11.65, "met_target": true}, {"date": "2026-02-16", "weekday": "Mon", "hours": 4.41, "met_target": false}, {"date": "2026-02-17", "weekday": "Tue", "hours": 10.5, "met_target": true}, {"date": "2026-02-18", "weekday": "Wed", "hours": 10.75, "met_target": true}, {"date": "2026-02-19", "weekday": "Thu", "hours": 4.11, "met_target": false}, {"date": "2026-02-20", "weekday": "Fri", "hours": 1.95, "met_target": false}, {"date": "2026-02-21", "weekday": "Sat", "hours": 6.65, "met_target": false}, {"date": "2026-02-22", "weekday": "Sun", "hours": 0, "met_target": false}, {"date": "2026-02-23", "weekday": "Mon", "hours": 0, "met_target": false}, {"date": "2026-02-24", "weekday": "Tue", "hours": 0, "met_target": false}, {"date": "2026-02-25", "weekday": "Wed", "hours": 0, "met_target": false}, {"date": "2026-02-26", "weekday": "Thu", "hours": 0, "met_target": false}, {"date": "2026-02-27", "weekday": "Fri", "hours": 0, "met_target": false}], "updated_at": "2026-02-22T02:49:10.082398+09:00"}